simpleai_lib/__init__.py
simpleai_lib-1.0.0.dist-info/METADATA
simpleai_lib-1.0.0.dist-info/WHEEL
simpleai_lib-1.0.0.dist-info/top_level.txt
simpleai_lib-1.0.0.dist-info/RECORD
