Metadata-Version: 2.1
Name: simpleai-lib
Version: 1.0.0
Summary: TODO
Home-page: https://github.com/pyhopper/pyhopper
Author: Simple-AI team
Author-email: rhasani@mit.edu
License: Apache Software License (Apache 2.0)
Platform: UNKNOWN
Classifier: Programming Language :: Python
Classifier: Programming Language :: Python :: 3.6
Classifier: Operating System :: Unix
Classifier: Operating System :: Microsoft :: Windows
Classifier: Operating System :: MacOS
Classifier: Intended Audience :: Science/Research
Classifier: Topic :: Scientific/Engineering
Classifier: Topic :: Software Development
Requires-Python: >3.6.0
Requires-Dist: packaging
Requires-Dist: future
Requires-Dist: pyhopper
Requires-Dist: keras-ncp
